LICENSE
MANIFEST.in
README.md
requirements.txt
setup.py
gptq/__init__.py
gptq/datautils.py
gptq/gptq.py
gptq/modelutils.py
gptq/quant.py
gptq/quant_cuda.cpp
gptq/quant_cuda_kernel.cu
gptq/utils.py
gptq/version.py
gptq.egg-info/PKG-INFO
gptq.egg-info/SOURCES.txt
gptq.egg-info/dependency_links.txt
gptq.egg-info/not-zip-safe
gptq.egg-info/requires.txt
gptq.egg-info/top_level.txt
gptq/models/bloom.py
gptq/models/opt.py